pyramid_i18n_wrapper/__init__.py
pyramid_i18n_wrapper/wtforms.py
pyramid_i18n_wrapper-1.2.3.dist-info/METADATA
pyramid_i18n_wrapper-1.2.3.dist-info/WHEEL
pyramid_i18n_wrapper-1.2.3.dist-info/licenses/LICENSE
pyramid_i18n_wrapper-1.2.3.dist-info/RECORD
